medoen/__init__.py
medoen/main.py
medoen-0.1.1.dist-info/METADATA
medoen-0.1.1.dist-info/WHEEL
medoen-0.1.1.dist-info/entry_points.txt
medoen-0.1.1.dist-info/top_level.txt
medoen-0.1.1.dist-info/RECORD
